README.rst
setup.cfg
setup.py
daexy/__init__.py
daexy/cmd.py
daexy.egg-info/PKG-INFO
daexy.egg-info/SOURCES.txt
daexy.egg-info/dependency_links.txt
daexy.egg-info/entry_points.txt
daexy.egg-info/not-zip-safe
daexy.egg-info/requires.txt
daexy.egg-info/top_level.txt